microbe_directory/__init__.py
microbe_directory/annotate.py
microbe_directory/clean_table.py
microbe_directory/composite_fields.py
microbe_directory/constants.py
microbe_directory/dataset_modification.py
microbe_directory/dataset_stats.py
microbe_directory/final_tables.py
microbe_directory/infill_fields.py
microbe_directory/taxa_tree.py
microbe_directory/cli/__init__.py
microbe_directory/cli/cli.py
microbe_directory/cli/cli_preprocessing.py
microbe_directory/cli/cli_stats.py
microbe_directory/comparisons/__init__.py
microbe_directory/comparisons/constants.py
microbe_directory/comparisons/microbe_directory_comparisons.py
microbe_directory/comparisons/statistics.py
microbe_directory/ncbi_tree/delnodes.dmp.gz
microbe_directory/ncbi_tree/division.dmp.gz
microbe_directory/ncbi_tree/gencode.dmp.gz
microbe_directory/ncbi_tree/merged.dmp.gz
microbe_directory/ncbi_tree/names.dmp.gz
microbe_directory/ncbi_tree/nodes.dmp.gz
microbe_directory/stored_final_tables/bacteria.csv.gz
microbe_directory/stored_final_tables/biocideResistanceProts.txt
microbe_directory/stored_final_tables/drugResistanceProts.txt
microbe_directory/stored_final_tables/eukaryota.csv.gz
microbe_directory/stored_final_tables/microbe-directory.csv.gz
microbe_directory/stored_final_tables/mobilityProts.txt
microbe_directory/stored_final_tables/repairProts.txt
microbe_directory/stored_final_tables/sporeProts.txt
microbe_directory/stored_final_tables/viruses.csv.gz
tests/__init__.py
tests/test_access_final_tables.py
tests/test_annotate.py
tests/test_microbe_directory_comparisons.py
tests/test_taxa_tree.py
microbe_directory-2.2.2.dist-info/METADATA
microbe_directory-2.2.2.dist-info/WHEEL
microbe_directory-2.2.2.dist-info/entry_points.txt
microbe_directory-2.2.2.dist-info/top_level.txt
microbe_directory-2.2.2.dist-info/RECORD
